{
    "config": {
        "type": "university",
        "term": { "singular": "大学", "plural": "大学" },
        "sections": 8,
        "hasHalfway": false,
        "showGrade": true,
        "specialTeams": ["日本学連選抜", "東海学連選抜"]
    },
    "eventName": "第52回全日本大学駅伝対校選手権大会",
    "year": 2020,
    "teams": [
        { "rank": 1, "name": "駒澤大学", "totalTime": "5:11:08", "runners": [{ "section": 1, "dist": "9.5km", "time": "27:13", "name": "加藤 淳", "grade": 4, "rank": 3 }, { "section": 2, "dist": "11.1km", "time": "32:19", "name": "花尾 恭輔", "grade": 1, "rank": 11 }, { "section": 3, "dist": "11.9km", "time": "34:07", "name": "鈴木 芽吹", "grade": 1, "rank": 5 }, { "section": 4, "dist": "11.8km", "time": "33:58", "name": "伊東 颯汰", "grade": 4, "rank": 7 }, { "section": 5, "dist": "12.4km", "time": "36:02", "name": "酒井 亮太", "grade": 2, "rank": 2 }, { "section": 6, "dist": "12.8km", "time": "37:45", "name": "山野 力", "grade": 2, "rank": 4 }, { "section": 7, "dist": "17.6km", "time": "52:10", "name": "小林 歩", "grade": 4, "rank": 4 }, { "section": 8, "dist": "19.7km", "time": "57:34", "name": "田澤 廉", "grade": 2, "rank": 1, "isNewRecord": false }] },
        { "rank": 2, "name": "東海大学", "totalTime": "5:11:31", "runners": [{ "section": 1, "dist": "9.5km", "time": "27:23", "name": "佐伯 陽生", "grade": 1, "rank": 7 }, { "section": 2, "dist": "11.1km", "time": "33:09", "name": "市村 朋樹", "grade": 3, "rank": 19 }, { "section": 3, "dist": "11.9km", "time": "33:45", "name": "塩澤 稀夕", "grade": 4, "rank": 2 }, { "section": 4, "dist": "11.8km", "time": "33:16", "name": "石原翔太郎", "grade": 1, "rank": 1, "isNewRecord": true }, { "section": 5, "dist": "12.4km", "time": "36:18", "name": "本間 敬大", "grade": 3, "rank": 4 }, { "section": 6, "dist": "12.8km", "time": "37:22", "name": "長田 駿佑", "grade": 3, "rank": 1, "isNewRecord": true }, { "section": 7, "dist": "17.6km", "time": "52:19", "name": "西田 壮志", "grade": 4, "rank": 6 }, { "section": 8, "dist": "19.7km", "time": "57:59", "name": "名取 燎太", "grade": 4, "rank": 3 }] },
        { "rank": 3, "name": "明治大学", "totalTime": "5:12:24", "runners": [{ "section": 1, "dist": "9.5km", "time": "27:15", "name": "児玉 真輝", "grade": 1, "rank": 5 }, { "section": 2, "dist": "11.1km", "time": "31:45", "name": "小袖 英人", "grade": 4, "rank": 4 }, { "section": 3, "dist": "11.9km", "time": "34:11", "name": "手嶋 杏丞", "grade": 3, "rank": 7 }, { "section": 4, "dist": "11.8km", "time": "33:55", "name": "櫛田 佳希", "grade": 2, "rank": 6 }, { "section": 5, "dist": "12.4km", "time": "36:40", "name": "金橋 佳佑", "grade": 3, "rank": 7 }, { "section": 6, "dist": "12.8km", "time": "37:27", "name": "大保 海士", "grade": 4, "rank": 2 }, { "section": 7, "dist": "17.6km", "time": "52:30", "name": "加藤 大誠", "grade": 2, "rank": 8 }, { "section": 8, "dist": "19.7km", "time": "58:41", "name": "鈴木 聖人", "grade": 3, "rank": 5 }] },
        { "rank": 4, "name": "青山学院大学", "totalTime": "5:12:42", "runners": [{ "section": 1, "dist": "9.5km", "time": "27:26", "name": "湯原 慶吾", "grade": 3, "rank": 10 }, { "section": 2, "dist": "11.1km", "time": "32:25", "name": "近藤幸太郎", "grade": 2, "rank": 13 }, { "section": 3, "dist": "11.9km", "time": "33:46", "name": "中村 唯翔", "grade": 2, "rank": 3 }, { "section": 4, "dist": "11.8km", "time": "33:54", "name": "岩見 秀哉", "grade": 4, "rank": 4 }, { "section": 5, "dist": "12.4km", "time": "35:47", "name": "佐藤 一世", "grade": 1, "rank": 1, "isNewRecord": true }, { "section": 6, "dist": "12.8km", "time": "38:18", "name": "山内 健登", "grade": 1, "rank": 9 }, { "section": 7, "dist": "17.6km", "time": "51:17", "name": "神林 勇太", "grade": 4, "rank": 1, "isNewRecord": false }, { "section": 8, "dist": "19.7km", "time": "59:49", "name": "吉田 圭太", "grade": 4, "rank": 11 }] },
        { "rank": 5, "name": "早稲田大学", "totalTime": "5:13:04", "runners": [{ "section": 1, "dist": "9.5km", "time": "27:18", "name": "辻 文哉", "grade": 1, "rank": 6 }, { "section": 2, "dist": "11.1km", "time": "31:51", "name": "井川 龍人", "grade": 2, "rank": 5 }, { "section": 3, "dist": "11.9km", "time": "33:42", "name": "中谷 雄飛", "grade": 3, "rank": 1, "isNewRecord": false }, { "section": 4, "dist": "11.8km", "time": "33:23", "name": "太田 直希", "grade": 3, "rank": 2 }, { "section": 5, "dist": "12.4km", "time": "36:54", "name": "菖蒲 敦司", "grade": 1, "rank": 9 }, { "section": 6, "dist": "12.8km", "time": "38:08", "name": "諸冨 湧", "grade": 1, "rank": 8 }, { "section": 7, "dist": "17.6km", "time": "52:38", "name": "鈴木 創士", "grade": 2, "rank": 9 }, { "section": 8, "dist": "19.7km", "time": "59:10", "name": "山口 賢助", "grade": 3, "rank": 6 }] },
        { "rank": 6, "name": "東洋大学", "totalTime": "5:13:15", "runners": [{ "section": 1, "dist": "9.5km", "time": "27:25", "name": "児玉 悠輔", "grade": 2, "rank": 9 }, { "section": 2, "dist": "11.1km", "time": "31:59", "name": "松山 和希", "grade": 1, "rank": 7 }, { "section": 3, "dist": "11.9km", "time": "34:14", "name": "佐藤 真優", "grade": 1, "rank": 9 }, { "section": 4, "dist": "11.8km", "time": "33:54", "name": "前田 義弘", "grade": 2, "rank": 4 }, { "section": 5, "dist": "12.4km", "time": "36:12", "name": "大澤 駿", "grade": 4, "rank": 3 }, { "section": 6, "dist": "12.8km", "time": "37:49", "name": "腰塚 遥人", "grade": 3, "rank": 5 }, { "section": 7, "dist": "17.6km", "time": "53:14", "name": "西山 和弥", "grade": 4, "rank": 11 }, { "section": 8, "dist": "19.7km", "time": "58:28", "name": "宮下 隼人", "grade": 3, "rank": 4 }] },
        { "rank": 7, "name": "帝京大学", "totalTime": "5:14:40", "runners": [{ "section": 1, "dist": "9.5km", "time": "27:34", "name": "小野隆一朗", "grade": 1, "rank": 18 }, { "section": 2, "dist": "11.1km", "time": "32:08", "name": "小野寺 悠", "grade": 4, "rank": 9 }, { "section": 3, "dist": "11.9km", "time": "33:54", "name": "鳥飼 悠生", "grade": 4, "rank": 4 }, { "section": 4, "dist": "11.8km", "time": "34:56", "name": "遠藤 大地", "grade": 3, "rank": 12 }, { "section": 5, "dist": "12.4km", "time": "36:42", "name": "橋本 尚斗", "grade": 3, "rank": 8 }, { "section": 6, "dist": "12.8km", "time": "37:43", "name": "増田 空", "grade": 4, "rank": 3 }, { "section": 7, "dist": "17.6km", "time": "52:14", "name": "星 岳", "grade": 4, "rank": 5 }, { "section": 8, "dist": "19.7km", "time": "59:29", "name": "細谷 翔馬", "grade": 3, "rank": 9 }] },
        { "rank": 8, "name": "順天堂大学", "totalTime": "5:14:43", "runners": [{ "section": 1, "dist": "9.5km", "time": "27:07", "name": "三浦 龍司", "grade": 1, "rank": 1, "isNewRecord": true }, { "section": 2, "dist": "11.1km", "time": "32:28", "name": "伊豫田達弥", "grade": 2, "rank": 14 }, { "section": 3, "dist": "11.9km", "time": "34:15", "name": "清水 颯大", "grade": 4, "rank": 10 }, { "section": 4, "dist": "11.8km", "time": "33:34", "name": "野村 優作", "grade": 2, "rank": 3 }, { "section": 5, "dist": "12.4km", "time": "36:23", "name": "石井 一希", "grade": 1, "rank": 5 }, { "section": 6, "dist": "12.8km", "time": "37:59", "name": "牧瀬 圭斗", "grade": 3, "rank": 7 }, { "section": 7, "dist": "17.6km", "time": "52:48", "name": "吉岡 智輝", "grade": 3, "rank": 10 }, { "section": 8, "dist": "19.7km", "time": "1:00:09", "name": "西澤 侑真", "grade": 2, "rank": 12 }] },
        { "rank": 9, "name": "國學院大學", "totalTime": "5:15:16", "runners": [{ "section": 1, "dist": "9.5km", "time": "27:15", "name": "島﨑 慎愛", "grade": 3, "rank": 4 }, { "section": 2, "dist": "11.1km", "time": "31:56", "name": "臼井 健太", "grade": 4, "rank": 6 }, { "section": 3, "dist": "11.9km", "time": "34:12", "name": "中西 大翔", "grade": 2, "rank": 8 }, { "section": 4, "dist": "11.8km", "time": "34:26", "name": "河東 寛大", "grade": 4, "rank": 8 }, { "section": 5, "dist": "12.4km", "time": "36:38", "name": "木付 琳", "grade": 3, "rank": 6 }, { "section": 6, "dist": "12.8km", "time": "38:43", "name": "伊地知賢造", "grade": 1, "rank": 10 }, { "section": 7, "dist": "17.6km", "time": "52:21", "name": "藤木 宏太", "grade": 3, "rank": 7 }, { "section": 8, "dist": "19.7km", "time": "59:45", "name": "殿地 琢朗", "grade": 3, "rank": 10 }] },
        { "rank": 10, "name": "東京国際大学", "totalTime": "5:17:05", "runners": [{ "section": 1, "dist": "9.5km", "time": "27:30", "name": "山谷 昌也", "grade": 2, "rank": 13 }, { "section": 2, "dist": "11.1km", "time": "32:00", "name": "丹所 健", "grade": 2, "rank": 8 }, { "section": 3, "dist": "11.9km", "time": "35:07", "name": "内田 光", "grade": 4, "rank": 15 }, { "section": 4, "dist": "11.8km", "time": "34:40", "name": "宗像 聖", "grade": 2, "rank": 9 }, { "section": 5, "dist": "12.4km", "time": "37:09", "name": "加藤 純平", "grade": 4, "rank": 13 }, { "section": 6, "dist": "12.8km", "time": "38:51", "name": "堀畑 佳吾", "grade": 2, "rank": 12 }, { "section": 7, "dist": "17.6km", "time": "53:54", "name": "佐伯 涼", "grade": 4, "rank": 16 }, { "section": 8, "dist": "19.7km", "time": "57:54", "name": "ルカ・ムセンビ", "grade": 2, "rank": 2 }] },
        { "rank": 11, "name": "中央学院大学", "totalTime": "5:19:25", "runners": [{ "section": 1, "dist": "9.5km", "time": "27:32", "name": "武川流以名", "grade": 2, "rank": 15 }, { "section": 2, "dist": "11.1km", "time": "32:29", "name": "小島 慎也", "grade": 2, "rank": 15 }, { "section": 3, "dist": "11.9km", "time": "34:26", "name": "栗原 啓吾", "grade": 3, "rank": 11 }, { "section": 4, "dist": "11.8km", "time": "35:49", "name": "戸口 豪琉", "grade": 4, "rank": 17 }, { "section": 5, "dist": "12.4km", "time": "37:00", "name": "中島 稜貴", "grade": 2, "rank": 10 }, { "section": 6, "dist": "12.8km", "time": "39:17", "name": "伊藤 秀虎", "grade": 1, "rank": 14 }, { "section": 7, "dist": "17.6km", "time": "53:36", "name": "畝 歩夢", "grade": 4, "rank": 12 }, { "section": 8, "dist": "19.7km", "time": "59:16", "name": "髙橋 翔也", "grade": 4, "rank": 7 }] },
        { "rank": 12, "name": "日本体育大学", "totalTime": "5:19:35", "runners": [{ "section": 1, "dist": "9.5km", "time": "27:33", "name": "岩室 天輝", "grade": 4, "rank": 17 }, { "section": 2, "dist": "11.1km", "time": "31:39", "name": "池田 耀平", "grade": 4, "rank": 3 }, { "section": 3, "dist": "11.9km", "time": "34:29", "name": "藤本 珠輝", "grade": 2, "rank": 12 }, { "section": 4, "dist": "11.8km", "time": "34:49", "name": "菅沼 隆佑", "grade": 4, "rank": 10 }, { "section": 5, "dist": "12.4km", "time": "37:00", "name": "福住 賢翔", "grade": 4, "rank": 10 }, { "section": 6, "dist": "12.8km", "time": "38:46", "name": "名村 樹哉", "grade": 2, "rank": 11 }, { "section": 7, "dist": "17.6km", "time": "53:52", "name": "大内 宏樹", "grade": 3, "rank": 15 }, { "section": 8, "dist": "19.7km", "time": "1:01:27", "name": "野上 翔大", "grade": 4, "rank": 15 }] },
        { "rank": 13, "name": "山梨学院大学", "totalTime": "5:20:03", "runners": [{ "section": 1, "dist": "9.5km", "time": "27:23", "name": "瀬戸 祐希", "grade": 4, "rank": 8 }, { "section": 2, "dist": "11.1km", "time": "32:21", "name": "松倉 唯斗", "grade": 3, "rank": 12 }, { "section": 3, "dist": "11.9km", "time": "36:31", "name": "橘田 大河", "grade": 2, "rank": 22 }, { "section": 4, "dist": "11.8km", "time": "34:49", "name": "新本 駿", "grade": 1, "rank": 10 }, { "section": 5, "dist": "12.4km", "time": "37:18", "name": "坪井 海門", "grade": 3, "rank": 14 }, { "section": 6, "dist": "12.8km", "time": "40:17", "name": "齋藤 有栄", "grade": 4, "rank": 18 }, { "section": 7, "dist": "17.6km", "time": "51:57", "name": "ポール・オニエゴ", "grade": 3, "rank": 3 }, { "section": 8, "dist": "19.7km", "time": "59:27", "name": "森山 真伍", "grade": 4, "rank": 8 }] },
        { "rank": 14, "name": "日本大学", "totalTime": "5:20:41", "runners": [{ "section": 1, "dist": "9.5km", "time": "27:31", "name": "小坂 友我", "grade": 3, "rank": 14 }, { "section": 2, "dist": "11.1km", "time": "32:41", "name": "松岡 竜矢", "grade": 2, "rank": 16 }, { "section": 3, "dist": "11.9km", "time": "35:30", "name": "若山 岳", "grade": 2, "rank": 17 }, { "section": 4, "dist": "11.8km", "time": "35:35", "name": "谷口 賢", "grade": 1, "rank": 15 }, { "section": 5, "dist": "12.4km", "time": "37:07", "name": "横山 徹", "grade": 4, "rank": 12 }, { "section": 6, "dist": "12.8km", "time": "37:56", "name": "樋口 翔太", "grade": 2, "rank": 6 }, { "section": 7, "dist": "17.6km", "time": "51:49", "name": "チャールズ・ドゥング", "grade": 2, "rank": 2 }, { "section": 8, "dist": "19.7km", "time": "1:02:32", "name": "武田悠太郎", "grade": 4, "rank": 18 }] },
        { "rank": 15, "name": "立命館大学", "totalTime": "5:22:26", "runners": [{ "section": 1, "dist": "9.5km", "time": "27:33", "name": "髙畑 凌太", "grade": 3, "rank": 16 }, { "section": 2, "dist": "11.1km", "time": "32:13", "name": "前川 紘導", "grade": 4, "rank": 10 }, { "section": 3, "dist": "11.9km", "time": "34:35", "name": "山田 真生", "grade": 2, "rank": 13 }, { "section": 4, "dist": "11.8km", "time": "34:59", "name": "永田 一輝", "grade": 3, "rank": 13 }, { "section": 5, "dist": "12.4km", "time": "37:21", "name": "谷口 晴信", "grade": 1, "rank": 15 }, { "section": 6, "dist": "12.8km", "time": "39:06", "name": "鈴木 雄太", "grade": 3, "rank": 13 }, { "section": 7, "dist": "17.6km", "time": "54:01", "name": "吉岡 遼人", "grade": 4, "rank": 17 }, { "section": 8, "dist": "19.7km", "time": "1:02:38", "name": "岡田 浩平", "grade": 4, "rank": 20 }] },
        { "rank": 16, "name": "城西大学", "totalTime": "5:23:29", "runners": [{ "section": 1, "dist": "9.5km", "time": "27:10", "name": "砂岡 拓磨", "grade": 3, "rank": 2 }, { "section": 2, "dist": "11.1km", "time": "31:37", "name": "菊地 駿弥", "grade": 4, "rank": 2 }, { "section": 3, "dist": "11.9km", "time": "34:35", "name": "菅原 伊織", "grade": 4, "rank": 13 }, { "section": 4, "dist": "11.8km", "time": "35:07", "name": "宮下 璃久", "grade": 3, "rank": 14 }, { "section": 5, "dist": "12.4km", "time": "38:08", "name": "藤井 正斗", "grade": 2, "rank": 16 }, { "section": 6, "dist": "12.8km", "time": "40:05", "name": "山本 樹", "grade": 1, "rank": 16 }, { "section": 7, "dist": "17.6km", "time": "53:39", "name": "山本 唯翔", "grade": 1, "rank": 13 }, { "section": 8, "dist": "19.7km", "time": "1:03:08", "name": "梶川 由稀", "grade": 4, "rank": 23 }] },
        { "rank": 17, "name": "皇學館大学", "totalTime": "5:27:25", "runners": [{ "section": 1, "dist": "9.5km", "time": "27:46", "name": "桑山 楓矢", "grade": 4, "rank": 21 }, { "section": 2, "dist": "11.1km", "time": "31:24", "name": "川瀬 翔矢", "grade": 4, "rank": 1, "isNewRecord": false }, { "section": 3, "dist": "11.9km", "time": "35:57", "name": "佐藤 楓馬", "grade": 1, "rank": 18 }, { "section": 4, "dist": "11.8km", "time": "36:37", "name": "竹内啓一郎", "grade": 2, "rank": 21 }, { "section": 5, "dist": "12.4km", "time": "38:18", "name": "鈴木 翔也", "grade": 3, "rank": 18 }, { "section": 6, "dist": "12.8km", "time": "40:54", "name": "柴田 龍一", "grade": 2, "rank": 21 }, { "section": 7, "dist": "17.6km", "time": "55:12", "name": "花井 秀輔", "grade": 2, "rank": 19 }, { "section": 8, "dist": "19.7km", "time": "1:01:17", "name": "上村 直也", "grade": 4, "rank": 14 }] },
        { "rank": 18, "name": "関西学院大学", "totalTime": "5:27:35", "runners": [{ "section": 1, "dist": "9.5km", "time": "28:20", "name": "田中 優樹", "grade": 1, "rank": 24 }, { "section": 2, "dist": "11.1km", "time": "33:25", "name": "沖見 史哉", "grade": 4, "rank": 20 }, { "section": 3, "dist": "11.9km", "time": "34:08", "name": "上田 颯汰", "grade": 2, "rank": 6 }, { "section": 4, "dist": "11.8km", "time": "35:41", "name": "守屋 和希", "grade": 1, "rank": 16 }, { "section": 5, "dist": "12.4km", "time": "38:29", "name": "井手 翔琉", "grade": 2, "rank": 21 }, { "section": 6, "dist": "12.8km", "time": "40:33", "name": "藪野 正大", "grade": 4, "rank": 20 }, { "section": 7, "dist": "17.6km", "time": "56:18", "name": "佐々木達平", "grade": 4, "rank": 21 }, { "section": 8, "dist": "19.7km", "time": "1:00:41", "name": "川田 信", "grade": 4, "rank": 13 }] },
        { "rank": 19, "name": "びわこ学院大学", "totalTime": "5:29:35", "runners": [{ "section": 1, "dist": "9.5km", "time": "27:52", "name": "井上 亮真", "grade": 3, "rank": 22 }, { "section": 2, "dist": "11.1km", "time": "34:10", "name": "小久保星音", "grade": 1, "rank": 24 }, { "section": 3, "dist": "11.9km", "time": "35:58", "name": "永井 友也", "grade": 1, "rank": 19 }, { "section": 4, "dist": "11.8km", "time": "36:11", "name": "多賀井悠斗", "grade": 1, "rank": 20 }, { "section": 5, "dist": "12.4km", "time": "38:19", "name": "原 陽宏", "grade": 4, "rank": 19 }, { "section": 6, "dist": "12.8km", "time": "40:08", "name": "小松原遊波", "grade": 4, "rank": 17 }, { "section": 7, "dist": "17.6km", "time": "54:39", "name": "杉岡 洸樹", "grade": 3, "rank": 18 }, { "section": 8, "dist": "19.7km", "time": "1:02:18", "name": "湯川 達矢", "grade": 4, "rank": 17 }] },
        { "rank": 20, "name": "広島経済大学", "totalTime": "5:32:03", "runners": [{ "section": 1, "dist": "9.5km", "time": "27:37", "name": "福永 恭平", "grade": 2, "rank": 20 }, { "section": 2, "dist": "11.1km", "time": "33:07", "name": "カランジャ・ジョスファット", "grade": 1, "rank": 17 }, { "section": 3, "dist": "11.9km", "time": "36:35", "name": "山﨑 優希", "grade": 2, "rank": 23 }, { "section": 4, "dist": "11.8km", "time": "36:52", "name": "山崎 達哉", "grade": 3, "rank": 22 }, { "section": 5, "dist": "12.4km", "time": "38:13", "name": "大竹 康平", "grade": 4, "rank": 17 }, { "section": 6, "dist": "12.8km", "time": "39:42", "name": "河原 洋太", "grade": 4, "rank": 15 }, { "section": 7, "dist": "17.6km", "time": "57:21", "name": "脇田 怜司", "grade": 4, "rank": 23 }, { "section": 8, "dist": "19.7km", "time": "1:02:36", "name": "谷澤 泰輝", "grade": 4, "rank": 19 }] },
        { "rank": 21, "name": "京都産業大学", "totalTime": "5:32:33", "runners": [{ "section": 1, "dist": "9.5km", "time": "27:29", "name": "北澤 涼雅", "grade": 3, "rank": 12 }, { "section": 2, "dist": "11.1km", "time": "33:08", "name": "坂口 博基", "grade": 3, "rank": 18 }, { "section": 3, "dist": "11.9km", "time": "35:27", "name": "時岡 宗生", "grade": 2, "rank": 16 }, { "section": 4, "dist": "11.8km", "time": "36:07", "name": "畠中 択実", "grade": 4, "rank": 19 }, { "section": 5, "dist": "12.4km", "time": "39:15", "name": "大石 朝陽", "grade": 1, "rank": 22 }, { "section": 6, "dist": "12.8km", "time": "41:16", "name": "松原渓士朗", "grade": 3, "rank": 22 }, { "section": 7, "dist": "17.6km", "time": "53:47", "name": "浦田 昂生", "grade": 3, "rank": 14 }, { "section": 8, "dist": "19.7km", "time": "1:06:04", "name": "片桐 健太", "grade": 4, "rank": 25 }] },
        { "rank": 22, "name": "信州大学", "totalTime": "5:36:25", "runners": [{ "section": 1, "dist": "9.5km", "time": "28:16", "name": "水野 裕司", "grade": 4, "rank": 23 }, { "section": 2, "dist": "11.1km", "time": "33:53", "name": "坪井 響己", "grade": 7, "rank": 23 }, { "section": 3, "dist": "11.9km", "time": "36:16", "name": "松林 直亮", "grade": 1, "rank": 20 }, { "section": 4, "dist": "11.8km", "time": "37:54", "name": "關 凱人", "grade": 3, "rank": 23 }, { "section": 5, "dist": "12.4km", "time": "38:23", "name": "吉岡 篤史", "grade": 2, "rank": 20 }, { "section": 6, "dist": "12.8km", "time": "42:09", "name": "石川 寛大", "grade": 2, "rank": 24 }, { "section": 7, "dist": "17.6km", "time": "56:31", "name": "野部 勇貴", "grade": 7, "rank": 22 }, { "section": 8, "dist": "19.7km", "time": "1:03:03", "name": "大島 宏輝", "grade": 4, "rank": 22 }] },
        { "rank": 23, "name": "札幌学院大学", "totalTime": "5:36:56", "runners": [{ "section": 1, "dist": "9.5km", "time": "27:29", "name": "ローレンス・グレ", "grade": 3, "rank": 11 }, { "section": 2, "dist": "11.1km", "time": "33:42", "name": "宇野 翔", "grade": 4, "rank": 22 }, { "section": 3, "dist": "11.9km", "time": "36:48", "name": "村上 一大", "grade": 1, "rank": 24 }, { "section": 4, "dist": "11.8km", "time": "36:03", "name": "谷川 純也", "grade": 1, "rank": 18 }, { "section": 5, "dist": "12.4km", "time": "39:45", "name": "田中 佑典", "grade": 4, "rank": 23 }, { "section": 6, "dist": "12.8km", "time": "41:29", "name": "大柳 達哉", "grade": 1, "rank": 23 }, { "section": 7, "dist": "17.6km", "time": "55:45", "name": "野村 隼斗", "grade": 4, "rank": 20 }, { "section": 8, "dist": "19.7km", "time": "1:05:55", "name": "工藤 真", "grade": 3, "rank": 24 }] },
        { "rank": 24, "name": "日本文理大学", "totalTime": "5:38:04", "runners": [{ "section": 1, "dist": "9.5km", "time": "27:36", "name": "山田 泰史", "grade": 4, "rank": 19 }, { "section": 2, "dist": "11.1km", "time": "33:26", "name": "米倉 光祐", "grade": 4, "rank": 21 }, { "section": 3, "dist": "11.9km", "time": "36:24", "name": "森口 翔平", "grade": 4, "rank": 21 }, { "section": 4, "dist": "11.8km", "time": "38:13", "name": "上原健太郎", "grade": 2, "rank": 24 }, { "section": 5, "dist": "12.4km", "time": "40:50", "name": "木原 雄大", "grade": 2, "rank": 24 }, { "section": 6, "dist": "12.8km", "time": "40:29", "name": "下郡 潤平", "grade": 4, "rank": 19 }, { "section": 7, "dist": "17.6km", "time": "58:04", "name": "久冨 大嗣", "grade": 2, "rank": 25 }, { "section": 8, "dist": "19.7km", "time": "1:03:02", "name": "関 穂嵩", "grade": 4, "rank": 21 }] },
        { "rank": 25, "name": "東北大学", "totalTime": "5:47:38", "runners": [{ "section": 1, "dist": "9.5km", "time": "30:14", "name": "立野 佑太", "grade": 7, "rank": 25 }, { "section": 2, "dist": "11.1km", "time": "37:06", "name": "田沼 怜", "grade": 4, "rank": 25 }, { "section": 3, "dist": "11.9km", "time": "38:41", "name": "石垣 雅生", "grade": 3, "rank": 25 }, { "section": 4, "dist": "11.8km", "time": "38:39", "name": "八鍬 佳紀", "grade": 2, "rank": 25 }, { "section": 5, "dist": "12.4km", "time": "40:58", "name": "牧野 雅紘", "grade": 3, "rank": 25 }, { "section": 6, "dist": "12.8km", "time": "42:14", "name": "脇田 陽平", "grade": 7, "rank": 25 }, { "section": 7, "dist": "17.6km", "time": "57:43", "name": "柚木 友哉", "grade": 8, "rank": 24 }, { "section": 8, "dist": "19.7km", "time": "1:02:03", "name": "松浦 崇之", "grade": 7, "rank": 16 }] }
    ]
}